continuous_delivery/__init__.py
continuous_delivery/continuous_delivery.py
continuous_delivery/credentials.py
continuous_delivery/exceptions.py
continuous_delivery/version.py
continuous_delivery/models/__init__.py
continuous_delivery/models/authorization_info.py
continuous_delivery/models/authorization_info_parameters.py
continuous_delivery/models/build_configuration.py
continuous_delivery/models/ci_artifact.py
continuous_delivery/models/ci_configuration.py
continuous_delivery/models/ci_result.py
continuous_delivery/models/provisioning_configuration.py
continuous_delivery/models/provisioning_configuration_source.py
continuous_delivery/models/provisioning_configuration_target.py
continuous_delivery/models/slot_swap_configuration.py
continuous_delivery/models/source_repository.py
pypi_task_demo-0.0.1.dist-info/DESCRIPTION.rst
pypi_task_demo-0.0.1.dist-info/METADATA
pypi_task_demo-0.0.1.dist-info/RECORD
pypi_task_demo-0.0.1.dist-info/WHEEL
pypi_task_demo-0.0.1.dist-info/metadata.json
pypi_task_demo-0.0.1.dist-info/top_level.txt
vsts_accounts/__init__.py
vsts_accounts/account.py
vsts_accounts/credentials.py
vsts_accounts/exceptions.py
vsts_accounts/version.py
vsts_accounts/models/__init__.py
vsts_accounts/models/account_create_info_internal.py
vsts_accounts/models/account_model.py
vsts_accounts/models/account_name_availability.py
vsts_accounts/models/account_preferences_internal.py
vsts_accounts/models/account_region.py
vsts_accounts/models/properties_collection.py
vsts_accounts/models/vss_json_collection_wrapper.py
vsts_accounts/models/vss_json_collection_wrapper_base.py
vsts_cd_manager/__init__.py
vsts_cd_manager/continuous_delivery_manager.py
vsts_info_provider/__init__.py
vsts_info_provider/exceptions.py
vsts_info_provider/version.py
vsts_info_provider/vsts_info_provider.py
vsts_info_provider/models/__init__.py
vsts_info_provider/models/collection_info.py
vsts_info_provider/models/repository_info.py
vsts_info_provider/models/team_project_info.py
vsts_info_provider/models/vsts_info.py
